lged/__init__.py
lged/app.py
lged/config.py
lged/downloader.py
lged/settings.py
lged-1.0.3.dist-info/LICENSE
lged-1.0.3.dist-info/METADATA
lged-1.0.3.dist-info/WHEEL
lged-1.0.3.dist-info/entry_points.txt
lged-1.0.3.dist-info/top_level.txt
lged-1.0.3.dist-info/RECORD
