Metadata-Version: 2.1
Name: lged
Version: 1.0.3
Summary: Library Genesis EBook Downloader CLI Tool
Home-page: https://github.com/bailang1208/lged
Author: Feilong Cui
Author-email: feilongcui@outlook.com
License: MIT
Keywords: libgen python package lged
Classifier: Environment :: Console
Classifier: Programming Language :: Python :: 3
Classifier: License :: OSI Approved :: MIT License
Classifier: Operating System :: OS Independent
Requires-Python: >=3.6
License-File: LICENSE
Requires-Dist: click (==8.1.3)
Requires-Dist: requests (==2.28.1)
Requires-Dist: beautifulsoup4 (==4.11.1)
Requires-Dist: tqdm (==4.64.1)
